brunata_api/__init__.py
brunata_api/const.py
brunata_api/test___init__.py
brunata_api/url_formatter.py
brunata_api-0.1.6.dist-info/LICENSE
brunata_api-0.1.6.dist-info/WHEEL
brunata_api-0.1.6.dist-info/METADATA
brunata_api-0.1.6.dist-info/RECORD
