Metadata-Version: 2.3
Name: brunata-api
Version: 0.1.6
Summary: A simple API library to communicate with Brunata Online
Author-email: YukiElectronics <yuki@yukie.dev>, Rien Maertens <rien.maertens@posteo.be>
Maintainer-email: YukiElectronics <yuki@yukie.dev>
Requires-Python: >=3.12, < 3.14
Requires-Dist: httpx>=0.27.0
Requires-Dist: fake-useragent>=2.0.0
Project-URL: Homepage, https://codeberg.org/YukiElectronics/brunata-api
